kaljax/kalman.py
kaljax-0.0.0.dist-info/METADATA
kaljax-0.0.0.dist-info/WHEEL
kaljax-0.0.0.dist-info/RECORD
