Metadata-Version: 2.1
Name: kaljax
Version: 0.0.0
Summary: Kalman filter implemented in JAX for GPU and CPU usage
Author: Alan
Requires-Python: >=3.9
Classifier: Programming Language :: Python :: 3
Classifier: Programming Language :: Python :: 3.9
Classifier: Programming Language :: Python :: 3.10
Classifier: Programming Language :: Python :: 3.11
Classifier: Programming Language :: Python :: 3.12
Requires-Dist: adbc-driver-sqlite (>=0.8.0,<0.9.0)
Requires-Dist: jax[gpu] (>=0.4.25,<0.5.0)
Requires-Dist: pyarrow (>=14.0.1,<15.0.0)
